{
  "configurations": [
    {
      "name": "VS-Debug-Windows",
      "generator": "Ninja",
      "configurationType": "Debug",
      "inheritEnvironments": [ "msvc_x64_x64" ],
      "buildRoot": "${projectDir}/build/${name}",
      "installRoot": "${projectDir}/install/${name}",
      "cmakeCommandArgs": "-LH",
      "buildCommandArgs": "-v",
      "ctestCommandArgs": "",
      "variables": [
        {
          "name": "CMAKE_PREFIX_PATH",
          "value": "C:/JUCE;C:/src/asorgejr_easyutils/build/Debug-VS/libeasyutils",
          "type": "STRING"
        },
        {
          "name": "CMAKE_MODULE_PATH",
          "value": "C:/tools/cmake-modules",
          "type": "STRING"
        },
        {
          "name": "TESTS_ENABLED",
          "value": "False",
          "type": "BOOL"
        },
        {
          "name": "CMAKE_TOOLCHAIN_FILE",
          "value": "C:/vcpkg/scripts/buildsystems/vcpkg.cmake",
          "type": "UNINITIALIZED"
        }
      ]
    }
  ]
}